PyMaSC/__init__.py
PyMaSC/calcmappablelen.py
PyMaSC/plot.py
PyMaSC/pymasc.py
PyMaSC/result.py
PyMaSC/stats.py
PyMaSC/core/__init__.py
PyMaSC/core/exceptions.py
PyMaSC/core/mappability.cpython-311-aarch64-linux-gnu.so
PyMaSC/core/mappability.pyi
PyMaSC/core/mappability.pyx
PyMaSC/core/mappability_310.c
PyMaSC/core/mappability_311.c
PyMaSC/core/mappability_312.c
PyMaSC/core/mappability_313.c
PyMaSC/core/mappability_38.c
PyMaSC/core/mappability_39.c
PyMaSC/core/readlen.cpython-311-aarch64-linux-gnu.so
PyMaSC/core/readlen.pyi
PyMaSC/core/readlen.pyx
PyMaSC/core/readlen_310.c
PyMaSC/core/readlen_311.c
PyMaSC/core/readlen_312.c
PyMaSC/core/readlen_313.c
PyMaSC/core/readlen_38.c
PyMaSC/core/readlen_39.c
PyMaSC/core/bitarray/__init__.py
PyMaSC/core/bitarray/bitarray.cpython-311-aarch64-linux-gnu.so
PyMaSC/core/bitarray/bitarray.pxd
PyMaSC/core/bitarray/bitarray.pyx
PyMaSC/core/bitarray/bitarray_310.c
PyMaSC/core/bitarray/bitarray_311.c
PyMaSC/core/bitarray/bitarray_312.c
PyMaSC/core/bitarray/bitarray_313.c
PyMaSC/core/bitarray/bitarray_38.c
PyMaSC/core/bitarray/bitarray_39.c
PyMaSC/core/bitarray/mscc.cpython-311-aarch64-linux-gnu.so
PyMaSC/core/bitarray/mscc.pyi
PyMaSC/core/bitarray/mscc.pyx
PyMaSC/core/bitarray/mscc_310.c
PyMaSC/core/bitarray/mscc_311.c
PyMaSC/core/bitarray/mscc_312.c
PyMaSC/core/bitarray/mscc_313.c
PyMaSC/core/bitarray/mscc_38.c
PyMaSC/core/bitarray/mscc_39.c
PyMaSC/core/successive/__init__.py
PyMaSC/core/successive/mscc.cpython-311-aarch64-linux-gnu.so
PyMaSC/core/successive/mscc.pyi
PyMaSC/core/successive/mscc.pyx
PyMaSC/core/successive/mscc_310.c
PyMaSC/core/successive/mscc_311.c
PyMaSC/core/successive/mscc_312.c
PyMaSC/core/successive/mscc_313.c
PyMaSC/core/successive/mscc_38.c
PyMaSC/core/successive/mscc_39.c
PyMaSC/core/successive/ncc.cpython-311-aarch64-linux-gnu.so
PyMaSC/core/successive/ncc.pyi
PyMaSC/core/successive/ncc.pyx
PyMaSC/core/successive/ncc_310.c
pymasc-1.0.0.dist-info/METADATA
pymasc-1.0.0.dist-info/WHEEL
pymasc-1.0.0.dist-info/entry_points.txt
pymasc-1.0.0.dist-info/top_level.txt
pymasc-1.0.0.dist-info/RECORD
pymasc-1.0.0.dist-info/licenses/LICENSE
