Metadata-Version: 2.4
Name: PyMaSC
Version: 1.0.0
Summary: Python implementation to calc mappability-sensitive cross-correlation for fragment length estimation and quality control for ChIP-Seq.
Author-email: Hayato Anzawa <anzawa@tohoku.ac.jp>
License: MIT
Project-URL: Homepage, https://github.com/ronin-gw/PyMaSC
Project-URL: Repository, https://github.com/ronin-gw/PyMaSC
Project-URL: Documentation, https://github.com/ronin-gw/PyMaSC
Project-URL: Bug Tracker, https://github.com/ronin-gw/PyMaSC/issues
Keywords: NGS,ChIP-Seq,bioinformatics,cross-correlation,mappability
Classifier: Development Status :: 5 - Production/Stable
Classifier: Environment :: Console
Classifier: Intended Audience :: Developers
Classifier: Intended Audience :: Science/Research
Classifier: Natural Language :: English
Classifier: Operating System :: MacOS :: MacOS X
Classifier: Operating System :: POSIX
Classifier: Operating System :: Unix
Classifier: Programming Language :: Cython
Classifier: Programming Language :: Python :: 3
Classifier: Programming Language :: Python :: 3.8
Classifier: Programming Language :: Python :: 3.9
Classifier: Programming Language :: Python :: 3.10
Classifier: Programming Language :: Python :: 3.11
Classifier: Programming Language :: Python :: 3.12
Classifier: Programming Language :: Python :: 3.13
Classifier: Programming Language :: Python :: Implementation :: CPython
Classifier: Topic :: Scientific/Engineering :: Bio-Informatics
Classifier: Topic :: Software Development :: Libraries :: Python Modules
Classifier: Typing :: Typed
Requires-Python: >=3.8
License-File: LICENSE
Requires-Dist: numpy>=1.21.0
Requires-Dist: pysam>=0.23.2
Requires-Dist: pyBigWig>=0.3.18
Requires-Dist: scipy>=1.7.0
Requires-Dist: matplotlib>=3.5.0
Requires-Dist: typing_extensions
Provides-Extra: test
Requires-Dist: pytest>=6.0; extra == "test"
Requires-Dist: pytest-cov; extra == "test"
Requires-Dist: pytest-xdist; extra == "test"
Requires-Dist: psutil>=5.8.0; extra == "test"
Provides-Extra: dev
Requires-Dist: PyMaSC[test]; extra == "dev"
Requires-Dist: Cython>=0.29.0; extra == "dev"
Requires-Dist: build; extra == "dev"
Requires-Dist: twine; extra == "dev"
Requires-Dist: mypy>=1.0.0; extra == "dev"
Requires-Dist: flake8; extra == "dev"
Requires-Dist: autopep8; extra == "dev"
Provides-Extra: release
Requires-Dist: cibuildwheel>=2.17.0; extra == "release"
Requires-Dist: build>=1.0.0; extra == "release"
Requires-Dist: twine>=4.0.0; extra == "release"
Dynamic: license-file
